 [{
  "id": 3,
  "name": "User 3",
  "id_str": "3",
  "url": "http://le.mu.rs",
  "profile_image_url": "http://a0.twimg.com/profile_images/1107557109/IMG_0027_normal.jpg",
  "following": true,
  "screen_name": "user3",
  "profile_image_url_https": "https://si0.twimg.com/profile_images/1107557109/IMG_0027_normal.jpg",
  "statuses_count": 18681,
  "location": "Appsterdam",
  "is_translator": false,
  "default_profile_image": false,
  "profile_background_color": "9AE4E8",
  "favourites_count": 1567,
  "friends_count": 1262,
  "description": "World's Toughest Programmer",
  "follow_request_sent": false
  },
  {
  "id": 4,
  "name": "User 4",
  "id_str": "4",
  "url": "http://le.mu.rs",
  "profile_image_url": "http://a0.twimg.com/profile_images/1107557109/IMG_0027_normal.jpg",
  "following": true,
  "screen_name": "user4",
  "profile_image_url_https": "https://si0.twimg.com/profile_images/1107557109/IMG_0027_normal.jpg",
  "statuses_count": 18681,
  "location": "Appsterdam",
  "is_translator": false,
  "default_profile_image": false,
  "profile_background_color": "9AE4E8",
  "favourites_count": 1567,
  "friends_count": 1262,
  "description": "World's Toughest Programmer",
  "follow_request_sent": false
  }
  ]